abetworks_agentwork/__init__.py
abetworks_agentwork/base.py
abetworks_agentwork/client.py
abetworks_agentwork/fastapi_agent.py
abetworks_agentwork/flask_agent.py
abetworks_agentwork-1.0.0.dist-info/licenses/LICENSE
abetworks_agentwork-1.0.0.dist-info/METADATA
abetworks_agentwork-1.0.0.dist-info/WHEEL
abetworks_agentwork-1.0.0.dist-info/top_level.txt
abetworks_agentwork-1.0.0.dist-info/RECORD
