Metadata-Version: 2.4
Name: abetworks-agentwork
Version: 1.0.0
Summary: SDK for building AI agents that integrate with Abetworks platform
Home-page: https://github.com/abetworks/abetworks-agentwork
Author: Abetworks
Author-email: contact@abetworks.in
Project-URL: Bug Tracker, https://github.com/abetworks/abetworks-agentwork/issues
Project-URL: Documentation, https://docs.abetworks.in
Project-URL: Source Code, https://github.com/abetworks/abetworks-agentwork
Project-URL: Website, https://abetworks.in
Keywords: ai agents automation abetworks sdk flask fastapi
Classifier: Development Status :: 5 - Production/Stable
Classifier: Intended Audience :: Developers
Classifier: Topic :: Software Development :: Libraries :: Python Modules
Classifier: Topic :: Software Development :: Libraries :: Application Frameworks
Classifier: License :: OSI Approved :: MIT License
Classifier: Programming Language :: Python :: 3
Classifier: Programming Language :: Python :: 3.8
Classifier: Programming Language :: Python :: 3.9
Classifier: Programming Language :: Python :: 3.10
Classifier: Programming Language :: Python :: 3.11
Classifier: Programming Language :: Python :: 3.12
Classifier: Framework :: Flask
Classifier: Framework :: FastAPI
Requires-Python: >=3.8
License-File: LICENSE
Requires-Dist: requests>=2.28.0
Requires-Dist: pydantic>=2.0.0
Requires-Dist: python-dotenv>=1.0.0
Provides-Extra: flask
Requires-Dist: flask>=2.3.0; extra == "flask"
Provides-Extra: fastapi
Requires-Dist: fastapi>=0.100.0; extra == "fastapi"
Requires-Dist: uvicorn>=0.23.0; extra == "fastapi"
Provides-Extra: all
Requires-Dist: flask>=2.3.0; extra == "all"
Requires-Dist: fastapi>=0.100.0; extra == "all"
Requires-Dist: uvicorn>=0.23.0; extra == "all"
Dynamic: author
Dynamic: author-email
Dynamic: classifier
Dynamic: description
Dynamic: description-content-type
Dynamic: home-page
Dynamic: keywords
Dynamic: license-file
Dynamic: project-url
Dynamic: provides-extra
Dynamic: requires-dist
Dynamic: requires-python
Dynamic: summary
